Metadata-Version: 1.1
Name: mynameiscandy
Version: 0.0.1
Summary: Who is Candy
Home-page: https://github.com/Perzyploy/
Author: Candy Catja
Author-email: ploymiony@gmail.com
License: MIT
Download-URL: https://github.com/Perzyploy/
Keywords: Candy,ASCII ART
Platform: UNKNOWN
Classifier: Development Status :: 3 - Alpha
Classifier: Intended Audience :: Education
Classifier: Topic :: Utilities
Classifier: License :: OSI Approved :: MIT License
Classifier: Programming Language :: Python :: 3
Classifier: Programming Language :: Python :: 3.4
Classifier: Programming Language :: Python :: 3.5
Classifier: Programming Language :: Python :: 3.6
Classifier: Programming Language :: Python :: 3.7
Classifier: Programming Language :: Python :: 3.8
Classifier: Programming Language :: Python :: 3.9
Classifier: Programming Language :: Python :: 3.10
